epsound/__init__.py
epsound/void.wav
epsound/wavplayer.py
epsound-0.1.1.dist-info/LICENSE
epsound-0.1.1.dist-info/METADATA
epsound-0.1.1.dist-info/WHEEL
epsound-0.1.1.dist-info/top_level.txt
epsound-0.1.1.dist-info/RECORD
