Metadata-Version: 2.1
Name: epsound
Version: 0.1.1
Summary: Sound player library
Home-page: https://github.com/EPC-MSU/epsound
Author: EPC MSU
Author-email: goncharovush@physlab.ru
License: MIT
Platform: UNKNOWN
Classifier: Programming Language :: Python :: 3
Classifier: License :: OSI Approved :: MIT License
Classifier: Operating System :: OS Independent
Requires-Python: >=3.4
License-File: LICENSE
Requires-Dist: simpleaudio (==1.0.2)
